veilmail/__init__.py
veilmail/main.py
VeilMail-1.0.8.dist-info/LICENSE
VeilMail-1.0.8.dist-info/METADATA
VeilMail-1.0.8.dist-info/WHEEL
VeilMail-1.0.8.dist-info/entry_points.txt
VeilMail-1.0.8.dist-info/top_level.txt
VeilMail-1.0.8.dist-info/RECORD
