Metadata-Version: 2.1
Name: VeilMail
Version: 1.0.8
Summary: A simple command-line email client using the 1secmail API.
Home-page: https://github.com/Zadeson/veilmail
Author: Ethen Dixon
Author-email: ethendixon@outlook.com
Classifier: Programming Language :: Python :: 3
Classifier: License :: OSI Approved :: MIT License
Classifier: Operating System :: OS Independent
Requires-Python: >=3.6
License-File: LICENSE
Requires-Dist: requests
Requires-Dist: rich
Requires-Dist: pyfiglet
Requires-Dist: yaspin
Requires-Dist: alive-progress
Requires-Dist: pyperclip
Requires-Dist: questionary
Requires-Dist: html2text
